{
  "1630639": "Guard",
  "1631260": "Guard",
  "1642358": "Guard",
  "203932": "Forward",
  "1628988": "Guard",
  "1630174": "Guard-Forward",
  "1630598": "Guard",
  "1641745": "Guard",
  "1641766": "Forward",
  "1641737": "Forward",
  "1642349": "Guard",
  "201143": "Center-Forward",
  "202692": "Guard",
  "1627936": "Guard",
  "1642505": "Guard",
  "203458": "Center",
  "1642024": "Forward-Center",
  "1642259": "Center",
  "1631214": "Guard",
  "1630578": "Center",
  "1641708": "Guard-Forward",
  "1629599": "Guard-Forward",
  "203083": "Center",
  "1641748": "Guard",
  "1629614": "Guard-Forward",
  "203952": "Forward",
  "1629014": "Guard",
  "1641710": "Guard",
  "203076": "Forward-Center",
  "1630162": "Guard",
  "1630264": "Forward",
  "1641817": "Forward",
  "1641810": "Guard",
  "1630574": "Center",
  "1641709": "Guard-Forward",
  "1630559": "Guard",
  "1630245": "Guard",
  "1628389": "Center-Forward",
  "1631248": "Guard",
  "1641767": "Guard",
  "1627732": "Guard-Forward",
  "1631097": "Guard-Forward",
  "1641731": "Guard",
  "202687": "Center",
  "1631104": "Guard",
  "1626171": "Forward",
  "1641752": "Forward",
  "203992": "Guard",
  "1629626": "Center-Forward",
  "1630538": "Guard",
  "203078": "Guard",
  "1642382": "Center",
  "1641764": "Guard",
  "1630527": "Guard",
  "1629634": "Forward",
  "1627742": "Forward",
  "1641706": "Forward",
  "1630314": "Guard",
  "1630296": "Forward",
  "1641729": "Forward",
  "1642355": "Guard",
  "201572": "Center",
  "1628971": "Guard-Forward",
  "1628981": "Forward-Center",
  "1631121": "Guard",
  "1642267": "Guard",
  "1627741": "Guard",
  "203468": "Guard",
  "1630595": "Guard",
  "1631216": "Guard",
  "1628997": "Forward",
  "1642353": "Guard",
  "1629629": "Forward-Guard",
  "1642285": "Guard",
  "1630560": "Guard",
  "1641715": "Forward",
  "1629661": "Forward",
  "1626166": "Guard",
  "1627747": "Guard",
  "1641717": "Guard",
  "1629646": "Center-Forward",
  "1631096": "Center-Forward",
  "1628449": "Forward",
  "1630537": "Guard",
  "1641753": "Forward",
  "101108": "Guard",
  "1631128": "Guard",
  "1631132": "Center",
  "1629643": "Forward",
  "203991": "Center",
  "1629632": "Guard",
  "1628998": "Forward",
  "1642262": "Forward",
  "1641732": "Guard",
  "1630175": "Guard",
  "1631306": "Forward",
  "1630658": "Center",
  "1631221": "Guard",
  "1629012": "Guard",
  "1630557": "Forward",
  "202709": "Guard",
  "1641854": "Guard",
  "1642385": "Forward",
  "1626156": "Guard",
  "1630618": "Guard",
  "1629610": "Guard-Forward",
  "1641747": "Forward",
  "1631342": "Guard-Forward",
  "1630227": "Guard",
  "1630625": "Forward",
  "1631207": "Forward",
  "1642261": "Forward",
  "203081": "Guard",
  "1641878": "Guard",
  "1627814": "Guard-Forward",
  "1629655": "Forward-Center",
  "1628464": "Forward-Center",
  "1642450": "Guard",
  "203957": "Guard",
  "203967": "Forward-Center",
  "1641727": "Guard-Forward",
  "1629636": "Guard",
  "1630561": "Guard",
  "1631223": "Forward",
  "1630558": "Guard",
  "1630549": "Center",
  "1628368": "Guard",
  "1629631": "Forward-Guard",
  "1629001": "Guard",
  "201599": "Center",
  "201942": "Guard-Forward",
  "1629731": "Forward-Center",
  "1629028": "Center",
  "1627749": "Guard",
  "1626153": "Guard",
  "1630166": "Forward",
  "203471": "Guard",
  "1641726": "Center",
  "1627884": "Forward",
  "1628401": "Guard",
  "1630217": "Guard",
  "1626164": "Guard",
  "1642269": "Guard",
  "1630170": "Guard-Forward",
  "1628415": "Guard-Forward",
  "1641794": "Forward",
  "1627734": "Forward-Center",
  "1631230": "Forward",
  "1642270": "Center",
  "1628378": "Guard",
  "1628978": "Guard",
  "1627827": "Forward",
  "203926": "Forward",
  "203110": "Forward",
  "1629234": "Forward-Center",
  "1641809": "Forward",
  "1631166": "Forward",
  "1630696": "Guard",
  "1629130": "Forward",
  "1641871": "Center",
  "203939": "Forward-Center",
  "1630700": "Guard",
  "1630604": "Forward",
  "203901": "Guard",
  "1641989": "Guard",
  "1641801": "Forward",
  "1641734": "Forward",
  "1642402": "Forward",
  "201569": "Guard",
  "1630679": "Guard",
  "1630596": "Center",
  "1630532": "Forward",
  "1627832": "Guard",
  "1641713": "Forward",
  "1629216": "Guard",
  "202066": "Guard-Forward",
  "1629726": "Guard",
  "203914": "Guard",
  "1627780": "Guard",
  "1629018": "Guard",
  "1627777": "Forward",
  "203507": "Forward",
  "1629048": "Center-Forward",
  "1641711": "Guard-Forward",
  "1629684": "Forward",
  "1628960": "Guard",
  "1627824": "Forward",
  "1630611": "Forward",
  "203084": "Forward",
  "1631127": "Forward",
  "1629312": "Forward",
  "1630529": "Forward",
  "1641816": "Forward",
  "1630193": "Guard",
  "1642403": "Forward",
  "1630171": "Forward-Guard",
  "1642268": "Guard",
  "1642384": "Forward",
  "1628392": "Center-Forward",
  "1630543": "Forward",
  "1630198": "Guard",
  "1641815": "Guard",
  "1630191": "Forward-Center",
  "1631209": "Guard",
  "1627826": "Center",
  "1631120": "Guard",
  "1630550": "Forward",
  "1629630": "Guard",
  "1642266": "Guard",
  "1631095": "Forward",
  "1631133": "Forward",
  "1629098": "Guard-Forward",
  "1642050": "Forward",
  "1631210": "Forward",
  "1630702": "Guard",
  "1631093": "Guard",
  "1630183": "Forward",
  "1630531": "Guard",
  "203109": "Forward",
  "1630256": "Forward",
  "1626143": "Center-Forward",
  "1642443": "Guard",
  "1631170": "Guard",
  "1631222": "Forward",
  "1627751": "Center",
  "1641779": "Forward",
  "1628973": "Guard",
  "1631105": "Center",
  "1630224": "Guard",
  "1641720": "Guard",
  "1630552": "Forward",
  "1629667": "Forward",
  "1629618": "Guard",
  "1630188": "Forward-Center",
  "1630591": "Guard",
  "1631114": "Guard-Forward",
  "1630592": "Forward",
  "1631288": "Forward",
  "1627750": "Guard",
  "1642347": "Guard",
  "1631123": "Guard",
  "201935": "Guard",
  "201949": "Forward",
  "1630164": "Center",
  "1642419": "Forward",
  "1641716": "Forward",
  "1630215": "Guard",
  "1642272": "Guard",
  "1631197": "Guard",
  "1628991": "Forward-Center",
  "1629020": "Forward",
  "1628386": "Center",
  "1629750": "Guard",
  "1629637": "Center-Forward",
  "1630643": "Center",
  "1627759": "Guard-Forward",
  "1641740": "Guard",
  "1641798": "Guard",
  "1629669": "Guard",
  "1642377": "Forward",
  "1631119": "Forward",
  "1642444": "",
  "1642281": "Guard-Forward",
  "1628369": "Forward-Guard",
  "1641789": "Guard",
  "1630288": "Guard",
  "201145": "Forward",
  "203924": "Forward",
  "1630526": "Forward",
  "1631110": "Forward",
  "1630579": "Center",
  "1642399": "Center",
  "1641724": "Guard",
  "1628975": "Guard",
  "202710": "Forward",
  "1629111": "Center",
  "204060": "Forward-Guard",
  "203954": "Center-Forward",
  "1628381": "Forward-Center",
  "1629723": "Guard",
  "1631098": "Guard",
  "163198": "",
  "1642277": "Guard",
  "1630548": "Guard",
  "202685": "Center",
  "1628371": "Forward",
  "1630228": "Forward",
  "1642367": "Forward",
  "203903": "Guard",
  "1630692": "Guard",
  "1641722": "Guard",
  "1629162": "Guard",
  "1641757": "Guard",
  "1629673": "Guard",
  "1641775": "Guard",
  "1630631": "Guard",
  "1630528": "Guard",
  "1630581": "Guard",
  "1630182": "Guard",
  "1628404": "Guard",
  "1631169": "Forward",
  "1629006": "Guard",
  "1626196": "Guard",
  "201950": "Guard",
  "1630577": "Forward",
  "1641763": "Forward",
  "1631124": "Guard",
  "203944": "Forward-Center",
  "1630551": "Guard-Forward",
  "1642348": "Forward",
  "1631303": "Forward",
  "203994": "Center",
  "1630231": "Forward",
  "1642354": "Guard",
  "1630539": "Center-Forward",
  "1626157": "Center-Forward",
  "1631255": "Forward-Center",
  "202695": "Forward",
  "1630811": "Guard",
  "1631099": "Forward",
  "1631232": "Forward",
  "1642276": "Center",
  "1629640": "Forward-Guard",
  "203482": "Forward-Center",
  "1626162": "Forward-Guard",
  "1629026": "Guard-Forward",
  "203484": "Guard",
  "1631165": "Guard",
  "1630553": "Guard",
  "1642352": "Forward",
  "1630556": "Forward",
  "201142": "Forward",
  "1628989": "Guard-Forward",
  "1628995": "Forward",
  "201567": "Forward-Center",
  "1641755": "Guard",
  "1629645": "Guard-Forward",
  "1626172": "Forward",
  "1641718": "Guard",
  "203114": "Forward",
  "1630165": "Guard",
  "202691": "Guard",
  "1641738": "Forward",
  "1641723": "Guard",
  "1627739": "Guard",
  "1631200": "Forward",
  "204001": "Forward-Center",
  "203937": "Forward-Guard",
  "1642271": "Center",
  "1628398": "Forward",
  "200768": "Guard",
  "1630283": "Center",
  "202681": "Guard",
  "1642273": "Forward",
  "1630163": "Guard",
  "1630205": "Forward",
  "1629013": "Guard",
  "1626204": "Forward-Center",
  "1628374": "Forward-Center",
  "2544": "Forward",
  "1631159": "Forward",
  "1631311": "Guard",
  "1641857": "Center",
  "1630322": "Forward",
  "1629022": "Guard-Forward",
  "1628366": "Guard",
  "1629652": "Guard",
  "1629029": "Forward-Guard",
  "1630568": "Center",
  "1628379": "Guard",
  "1628436": "Center-Forward",
  "1631247": "Forward",
  "1630644": "Guard",
  "1630201": "Guard",
  "1631103": "Forward",
  "1627763": "Guard",
  "1642502": "Forward",
  "27791": "",
  "1627736": "Guard",
  "1628370": "Guard",
  "1630699": "Forward",
  "1630542": "Forward",
  "1630585": "Guard",
  "1631204": "Guard",
  "203935": "Guard",
  "1631109": "Center",
  "1628365": "Guard",
  "202693": "Forward",
  "1628963": "Forward",
  "1630222": "Guard",
  "203486": "Forward-Center",
  "1641824": "Forward",
  "1629680": "Guard-Forward",
  "1630346": "Forward",
  "1631108": "Guard",
  "1629622": "Guard-Forward",
  "1628467": "Forward",
  "1641721": "Forward",
  "1630695": "Center",
  "1629008": "Forward",
  "1628969": "Guard-Forward",
  "201144": "Guard",
  "1628970": "Forward",
  "1630540": "Guard",
  "1641936": "Forward",
  "1629011": "Center-Forward",
  "1628964": "Center",
  "1628420": "Guard",
  "1629021": "Forward-Center",
  "1629650": "Center",
  "1630541": "Guard",
  "1631243": "Forward",
  "1631217": "Forward",
  "1626167": "Center-Forward",
  "1642368": "Center",
  "1641772": "Forward",
  "1630230": "Forward",
  "1631466": "Guard",
  "1629675": "Center-Forward",
  "1629674": "Center",
  "1629651": "Center",
  "1630208": "Center",
  "1641733": "Guard",
  "1629638": "Guard",
  "201587": "Guard-Forward",
  "203999": "Center",
  "1631107": "Forward",
  "202696": "Center",
  "1641730": "Forward-Center",
  "1626181": "Guard",
  "1628384": "Forward-Guard",
  "1630167": "Forward",
  "1630534": "Guard",
  "1641765": "Forward",
  "1630168": "Forward-Center",
  "1631115": "Center",
  "1631131": "Forward-Center",
  "1629052": "Forward-Guard",
  "1642345": "Forward",
  "1631172": "Forward",
  "200782": "Forward",
  "1629023": "Forward",
  "1628408": "Guard-Forward",
  "1641790": "Center",
  "1631094": "Forward",
  "1627783": "Forward",
  "1626192": "Guard",
  "1630311": "Guard",
  "1631116": "Forward",
  "1630172": "Forward",
  "201988": "Guard",
  "202331": "Forward",
  "1630194": "Forward",
  "1630202": "Guard",
  "1641796": "Guard",
  "1631250": "Forward",
  "1631212": "Guard",
  "1630762": "Forward",
  "1630173": "Forward",
  "1629656": "Guard",
  "1631245": "Guard",
  "1642439": "Guard",
  "1642366": "Center",
  "1629628": "Forward-Guard",
  "1642484": "Guard",
  "1641712": "Guard-Forward",
  "1641736": "Guard",
  "1642263": "Guard",
  "202704": "Guard",
  "1626158": "Forward",
  "1641741": "Guard",
  "1642434": "Forward",
  "1642265": "Guard",
  "1629057": "Center-Forward",
  "1631199": "Guard-Forward",
  "1641842": "Forward",
  "1626220": "Forward",
  "203497": "Center",
  "1629060": "Forward",
  "201566": "Guard",
  "1642346": "Forward",
  "1631157": "Guard",
  "1630573": "Forward",
  "1630241": "Guard",
  "1630572": "Forward-Center",
  "1630583": "Forward-Center",
  "1630703": "Guard",
  "1630567": "Forward-Guard",
  "1630590": "Guard",
  "203552": "Guard",
  "1631101": "Guard",
  "1628983": "Guard",
  "1629003": "Guard",
  "1631321": "Guard",
  "1631323": "Forward",
  "1627746": "Forward-Center",
  "203915": "Guard",
  "1642461": "Forward",
  "1630649": "Guard",
  "201939": "Guard",
  "1642264": "Guard",
  "203500": "Center",
  "1629004": "Guard-Forward",
  "204456": "Guard",
  "201959": "Forward",
  "1629659": "Guard",
  "1642379": "Guard",
  "1631106": "Forward",
  "1627752": "Forward",
  "1641707": "Forward",
  "1629611": "Guard-Forward",
  "1630545": "Guard-Forward",
  "1626179": "Guard",
  "1630678": "Forward",
  "1628418": "Center-Forward",
  "1642275": "Forward",
  "203501": "Guard-Forward",
  "202699": "Forward",
  "1642449": "Forward",
  "1628396": "Center-Forward",
  "1628470": "Forward",
  "1641787": "Forward",
  "1641739": "Forward",
  "1629027": "Guard",
  "1631218": "Forward",
  "1630200": "Guard",
  "1630544": "Guard",
  "1630570": "Guard-Forward",
  "1642280": "Forward",
  "1630243": "Guard",
  "1641725": "Guard",
  "1641998": "Center",
  "1626168": "Forward",
  "1630530": "Forward",
  "202684": "Center-Forward",
  "1641774": "Forward",
  "1641783": "Forward",
  "1641803": "Guard",
  "1629660": "Guard-Forward",
  "1631102": "Guard",
  "1629639": "Guard",
  "1642278": "Guard",
  "1641890": "Forward",
  "1630169": "Guard",
  "1631213": "Forward",
  "1630178": "Guard",
  "1630623": "Guard",
  "1626145": "Guard",
  "1642279": "Center",
  "1641705": "Forward-Center",
  "1631246": "Guard",
  "1628427": "Forward",
  "1630249": "Guard",
  "1631117": "Center",
  "1628976": "Center-Forward",
  "1631111": "Guard",
  "1630214": "Forward",
  "1642530": "Guard",
  "1641879": "Guard",
  "1642274": "Center",
  "1642258": "Forward",
  "1628380": "Forward-Center",
  "1641744": "Center",
  "203897": "Guard",
  "1630192": "Forward-Center",
  "1630533": "Forward",
  "1629627": "Forward",
  "1642389": "Guard"
}